{"title":"Herbstfärbung in Maine","caption":"Herbstfärbung in Maine","desc":"Für gewöhnlich erreicht die Herbstfärbung der Bäume und Sträucher im Acadia-Nationalpark Mitte Oktober ihren Höhepunkt. Die Landschaft verwandelt sich dann in ein gelbes und orangenes Farbenmeer, und die hier abgebildeten Heidelbeersträucher fügen der bunten Palette noch ein kräftiges Rot hinzu.","copyright":"Heidelbeersträucher im Acadia-Nationalpark, Maine, USA (© Danita Delimont/Gallo Images/Getty Images Plus)","copyrightlink":"/search?q=Acadia-Nationalpark&form=hpcapt&filters=HpDate%3a%2220191015_2200%22","date":"20191015","image":{"name":"OHR.AcadiaBlueberries_DE-DE8466616364.jpg","hd":"/images/001B68DF455CD783A310947A89AEEB9A7DC1E5B3BD6C15C04BCAC2A02E146266.jpg","tmb":"/images/3FED97192566ECF352F5CFA1F4D48C415E5513B350909E895BBE0A17DFD7A31A.jpg","binghd":"https://www.bing.com/th?id=OHR.AcadiaBlueberries_DE-DE8466616364_1920x1080.jpg&rf=LaDigue_1920x1080.jpg&pid=hp","bingtmb":"https://www.bing.com/th?id=OHR.AcadiaBlueberries_DE-DE8466616364_tmb.jpg"}}