{"title":"Hier war Frank Gehry am Werk","caption":"Nach einem Entwurf von Frank Gehry","desc":"Zum heutigen Internationalen Tag der Architektur zeigen wir Ihnen auf unserer Startseite die „Cleveland Clinic Lou Ruvo Center for Brain Health“ in Las Vegas im US-Bundesstaat Nevada. Der Entwurf für dieses im Jahr 2005 errichtete, spektakuläre Gebäude stammt von einem der renommiertesten Architekten der Gegenwart: Frank Gehry.","copyright":"Lou Ruvo Center for Brain Health in Las Vegas, Nevada, USA. Anlässlich des Internationalen Tages der Architektur (© Garry Belinsky/Offset)","copyrightlink":"/search?q=Internationaler+Tag+der+Architektur+erster+Montag+Oktober&form=hpcapt&filters=HpDate%3a%2220191006_2200%22","date":"20191006","image":{"name":"OHR.LouRuvo_DE-DE9848332659.jpg","hd":"/images/5A22E1EB5E0E13FBFB4F0AB549784A162A08FDAEAED4514A7D75464FD8A533A7.jpg","tmb":"/images/A9DFAA132EE980DBC12DF33908B487C4B08690793F9C9E712B09ED2AFDDAD622.jpg","binghd":"https://www.bing.com/th?id=OHR.LouRuvo_DE-DE9848332659_1920x1080.jpg&rf=LaDigue_1920x1080.jpg&pid=hp","bingtmb":"https://www.bing.com/th?id=OHR.LouRuvo_DE-DE9848332659_tmb.jpg"}}