{"title":"1, 1, 2, 3 : C’est la Journée de Fibonacci !","caption":"1, 1, 2, 3 : C’est la Journée de Fibonacci !","desc":"Selon les anglo-saxon (qui ont leurs propres règles), la date d’aujourd’hui, le 23 novembre, s'écrit ainsi : 11.23 (le mois avant le jour…) et donc : 1,1,2,3 – correspondant alors à la suite de Fibonacci. De la même manière, le nombre de feuilles sur cet Agave Victoria-Reginae, que l’on voit sur l’image d’aujourd’hui, correspond aussi à la suite de Fibonacci. Cette suite unique fut présentée par le mathématicien italien Leonardo da Pisa (connu après sa mort sous le nom de Fibonacci) à l’Europe en 1202, à travers son œuvre « Liber Abaci ». Ce livre commence par décrire le système de numérotation indo-arabe ou « Modus Indorum » - 0 1 2 3 4 5 6 7 8 9 – et démontre comment son utilisation pourrait simplifier le commerce et permettre des calculs plus rapides et plus faciles (à l’époque, la majeure partie de l’Europe utilisait la numérotation romaine).","copyright":"Une agave pour la Journée de Fibonacci (© Moab Republic/Shutterstock)","copyrightlink":"/search?q=suite+fibonacci&form=hpcapt&filters=HpDate%3a%2220191122_2300%22","date":"20191122","image":{"name":"OHR.QueenVictoriaAgave_FR-FR5509623541.jpg","hd":"/images/FAFBD4EF6EB838BD84B82E1C58C6C916076A4F6545D5E562AD9B4363EAB80D3B.jpg","tmb":"/images/12A6395956C8075F4197E229670C66F88A3A28A8AA376750F796F5AB89AE3215.jpg","binghd":"https://www.bing.com/th?id=OHR.QueenVictoriaAgave_FR-FR5509623541_1920x1080.jpg&rf=LaDigue_1920x1080.jpg&pid=hp","bingtmb":"https://www.bing.com/th?id=OHR.QueenVictoriaAgave_FR-FR5509623541_tmb.jpg"}}