{"title":"Coniferous forest, Vosges Mountains, France ","caption":"Coniferous forest, Vosges Mountains, France ","desc":null,"copyright":"Coniferous forest, Vosges Mountains, France (© Radomir Jakubowski/Minden Pictures)","copyrightonly":"© Radomir Jakubowski/Minden Pictures","copyrightlink":"javascript:void(0)","date":"20190918","image":{"name":"OHR.SunbeamsForest_ROW0696490671.jpg","hd":"/image/e3b0c44298fc1c149afbf4c8996fb92427ae41e4649b934ca495991b7852b855.jpg","tmp":"/image/7970f804215a4800ce2f33b0cf9e6ab41c1b01fc74e9d567ad576a212b479390.jpg","binghd":"https://cn.bing.com/th?id=OHR.SunbeamsForest_ROW0696490671_1920x1080.jpg&rf=LaDigue_1920x1080.jpg&pid=hp","bingtmb":"https://www.bing.com/th?id=OHR.SunbeamsForest_ROW0696490671_tmb.jpg"}}