{"title":"今日は｢国際ホッキョクグマの日｣","caption":"｢ホッキョクグマ｣カナダ, ハドソン湾","desc":"今日は｢国際ホッキョクグマの日｣。民間の保護団体である｢ポーラーベアーズ・インターナショナル｣が制定し、世界中に広まりました。地球温暖化の影響をもっとも受ける動物と呼ばれるホッキョクグマの保護を目的とした日です…","copyright":"｢ホッキョクグマ｣カナダ, ハドソン湾 (© Ralph A. Clevenger/Tandem Stills + Motion)","copyrightlink":"/search?q=%e3%83%9b%e3%83%83%e3%82%ad%e3%83%a7%e3%82%af%e3%82%b0%e3%83%9e&form=hpcapt&filters=HpDate%3a%2220200226_1500%22","date":"20200226","image":{"name":"OHR.PolarBearDay_JA-JP8969164622.jpg","hd":"/images/A339B6F6957471901A7C7819B83FDF048E995502C8E0FFE4DB2B38D89796B620.jpg","tmb":"/images/D430DA1116BE5CE7BF3023D61451D49BB9155B39118236ABAF72DC76C510A0E5.jpg","binghd":"https://www.bing.com/th?id=OHR.PolarBearDay_JA-JP8969164622_1920x1080.jpg&rf=LaDigue_1920x1080.jpg&pid=hp","bingtmb":"https://www.bing.com/th?id=OHR.PolarBearDay_JA-JP8969164622_tmb.jpg"}}