{"title":"Aujourd’hui, on donne tout !","caption":"C’est Giving Tuesday !","desc":"En voyant ce macareux moine offrir ces magnifiques brindilles à sa compagne pour fabriquer un nid d’enfer, nous avons pensé qu’il ferait une mascotte idéale en cette journée de Giving Tuesday ! Vous ne savez pas ce qu’est Giving Tuesday ? On vous explique : l’évènement fut établi en 2012 pour encourager les gestes de générosité durant la période des fêtes de fin d’année, alors que « consommer » semble être la préoccupation principale d’un grand nombre d’entre nous.","copyright":"Macareux moine male offrant à sa compagne de quoi faire un nid, île de Skomer, Pays-de Galle (© Danny Green/Minden Pictures)","copyrightlink":"/search?q=macareux+moine&form=hpcapt&filters=HpDate%3a%2220191202_2300%22","date":"20191202","image":{"name":"OHR.PuffinSharing_FR-FR7967743517.jpg","hd":"/images/57C29EDDFA903050DD044E02D1BA1CD262B4F0D8440E142E3FEC786761C1D8CF.jpg","tmb":"/images/30280F68146FD62D488B85C8A44EBBE6C594672A33FE359048F6D8DD7B7F0307.jpg","binghd":"https://www.bing.com/th?id=OHR.PuffinSharing_FR-FR7967743517_1920x1080.jpg&rf=LaDigue_1920x1080.jpg&pid=hp","bingtmb":"https://www.bing.com/th?id=OHR.PuffinSharing_FR-FR7967743517_tmb.jpg"}}