{"images":[{"startdate":"20190924","fullstartdate":"201909242200","enddate":"20190925","url":"/th?id=OHR.LofotenSurfing_DE-DE1054925194_1920x1080.jpg&rf=LaDigue_1920x1080.jpg&pid=hp","urlbase":"/th?id=OHR.LofotenSurfing_DE-DE1054925194","copyright":"Arktischer Surftrip auf den Lofoten, Norwegen. Anlässlich der Lofoten Masters (© Nicolás Pina/Tandem Stills + Motion)","copyrightlink":"/search?q=Lofoten+Inseln&form=hpcapt&filters=HpDate%3a%2220190924_2200%22","title":"Entspannen in der Arktis","caption":"Traumhafter Sonnenuntergang in Norwegen","copyrightonly":"© Nicolás Pina/Tandem Stills + Motion","desc":"Surfer aus Norwegen und der ganzen Welt treffen sich jedes Jahr im September in Unstad, einem kleinen Dorf auf den norwegischen Lofoten-Inseln, um an den Lofoten Masters teilzunehmen, einem Contest, der sich als „der nördlichste Surf-Wettbewerb der Welt“ bezeichnet.","date":"25. Sep. 2019","bsTitle":"Entspannen in der Arktis","quiz":"/search?q=Bing+homepage+quiz&filters=WQOskey:%22HPQuiz_20190924_LofotenSurfing%22&FORM=HPQUIZ","wp":true,"hsh":"88d0f8ae594b123d9e3ec1cddbb6f48a","drk":1,"top":1,"bot":1,"hs":[],"og":{"img":"https://www.bing.com/th?id=OHR.LofotenSurfing_DE-DE1054925194_tmb.jpg","title":"Traumhafter Sonnenuntergang in Norwegen","desc":"Surfer aus Norwegen und der ganzen Welt treffen sich jedes Jahr im September in Unstad, einem kleinen Dorf auf den norwegischen Lofoten…","hash":"CIRbiKWrKNUpuxTGx3tYN+O8L6jMm/NkTU8vDFUnzuk="}}],"tooltips":{"loading":"Wird geladen...","previous":"Vorheriges Bild","next":"Nächstes Bild","walle":"Dieses Bild steht nicht zum Download als Hintergrundbild zur Verfügung.","walls":"Dieses Bild herunterladen. Dieses Bild darf nur als Hintergrundbild verwendet werden."}}