{"images":[{"startdate":"20191122","fullstartdate":"201911222300","enddate":"20191123","url":"/th?id=OHR.QueenVictoriaAgave_FR-FR5509623541_1920x1080.jpg&rf=LaDigue_1920x1080.jpg&pid=hp","urlbase":"/th?id=OHR.QueenVictoriaAgave_FR-FR5509623541","copyright":"Une agave pour la Journée de Fibonacci (© Moab Republic/Shutterstock)","copyrightlink":"/search?q=suite+fibonacci&form=hpcapt&filters=HpDate%3a%2220191122_2300%22","title":"1, 1, 2, 3 : C’est la Journée de Fibonacci !","caption":"1, 1, 2, 3 : C’est la Journée de Fibonacci !","copyrightonly":"© Moab Republic/Shutterstock","desc":"Selon les anglo-saxon (qui ont leurs propres règles), la date d’aujourd’hui, le 23 novembre, s'écrit ainsi : 11.23 (le mois avant le jour…) et donc : 1,1,2,3 – correspondant alors à la suite de Fibonacci. De la même manière, le nombre de feuilles sur cet Agave Victoria-Reginae, que l’on voit sur l’image d’aujourd’hui, correspond aussi à la suite de Fibonacci. Cette suite unique fut présentée par le mathématicien italien Leonardo da Pisa (connu après sa mort sous le nom de Fibonacci) à l’Europe en 1202, à travers son œuvre « Liber Abaci ». Ce livre commence par décrire le système de numérotation indo-arabe ou « Modus Indorum » - 0 1 2 3 4 5 6 7 8 9 – et démontre comment son utilisation pourrait simplifier le commerce et permettre des calculs plus rapides et plus faciles (à l’époque, la majeure partie de l’Europe utilisait la numérotation romaine).","date":"23 nov. 2019","bsTitle":"1, 1, 2, 3 : C’est la Journée de Fibonacci !","quiz":"/search?q=Bing+homepage+quiz&filters=WQOskey:%22HPQuiz_20191122_QueenVictoriaAgave%22&FORM=HPQUIZ","wp":true,"hsh":"8f623201d398ea24b473c6bc6d4ef8d3","drk":1,"top":1,"bot":1,"hs":[],"og":{"img":"https://www.bing.com/th?id=OHR.QueenVictoriaAgave_FR-FR5509623541_tmb.jpg","title":"1, 1, 2, 3 : C'est la Journée de Fibonacci !","desc":"Selon les anglo-saxon (qui ont leurs propres règles), la date d’aujourd’hui, le 23 novembre, s'écrit ainsi : 11.23 (le mois avant le jour…","hash":"ubD1DZl5LEY/1qna/yquf/24bfT/D4NqtobAaIEg6ow="}}],"tooltips":{"loading":"Chargement en cours...","previous":"Image précédente","next":"Image suivante","walle":"Cette image n’est pas disponible pour téléchargement en tant que papier peint.","walls":"Téléchargez cette image. L’utilisation de cette image est réservée à des fins de papier peint uniquement."}}