{"images":[{"startdate":"20200302","fullstartdate":"202003022300","enddate":"20200303","url":"/th?id=OHR.SpectralTarsiers_ES-ES4249983932_1920x1080.jpg&rf=LaDigue_1920x1080.jpg&pid=hp","urlbase":"/th?id=OHR.SpectralTarsiers_ES-ES4249983932","copyright":"Tarseros fantasma en un ficus de la reserva natural Tangkoko Batuangus, Indonesia (© Ondrej Prosicky/Shutterstock)","copyrightlink":"/search?q=tarsero+fantasma&FORM=hpcapt&filters=HpDate%3a%2220200302_2300%22","title":"El Día de la Naturaleza","caption":"Los tarseros y la biodiversidad","copyrightonly":"© Ondrej Prosicky/Shutterstock","desc":"No necesitamos ninguna excusa para mostrarte a estas fascinantes criaturas, pero da la casualidad de que hoy es el Día de la Naturaleza que celebra Naciones Unidas. El tema de este año es la “Sostenibilidad de la vida en la Tierra y la biodiversidad”. Y precisamente, la reserva natural Indonesia de Tangkoko Batuangus, donde fue tomada nuestra imagen, es un ejemplo de esa biodiversidad, porque alberga cientos de especies de plantas, mamíferos, aves, reptiles y anfibios.","date":"3 mar., 2020","quiz":"/search?q=Bing+homepage+quiz&filters=WQOskey:%22HPQuiz_20200302_SpectralTarsiers%22&FORM=HPQUIZ","wp":true,"hsh":"12848c891c6026c9d341f0e6a0f4000c","drk":1,"top":1,"bot":1,"hs":[],"og":{"img":"https://www.bing.com/th?id=OHR.SpectralTarsiers_ES-ES4249983932_tmb.jpg","title":"Los tarseros y la biodiversidad","desc":"No necesitamos ninguna excusa para mostrarte a estas fascinantes criaturas, pero da la casualidad de que hoy es el Día de la Naturaleza que…","hash":"Hz/EeclHtihioJSKEP+WFWpD+miBkvAaed/zY8KVYDo="}}],"tooltips":{"loading":"S'està carregant...","previous":"Imatge anterior","next":"Imatge següent","walle":"Aquesta imatge no està disponible per descarregar-la com a empaperat.","walls":"Baixa la imatge. Només la pots utilitzar com a empaperat de l'escriptori."}}