{"title":"今日は｢化学の日｣","caption":"｢液体窒素の爆発｣","desc":"今日は｢化学の日｣。物質量｢モル｣ を構成する粒子数を表す定数｢6.02ｘ\"10の23乗\"｣にちなんで、10月23日に制定されました。さらに、今週は｢化学週間｣として、さまざまな化学普及イベントが予定されています…","copyright":"｢液体窒素の爆発｣ (© Sunny/Getty Images)","copyrightlink":"/search?q=%e6%b6%b2%e4%bd%93%e7%aa%92%e7%b4%a0&form=hpcapt&filters=HpDate%3a%2220191022_1500%22","date":"20191022","image":{"name":"OHR.LiquidNitrogen_JA-JP8558852359.jpg","hd":"/images/1EB618C4747C7E3A1C4179EC0F47C2FA51DC168929758F9D6064EBE5F92977D6.jpg","tmb":"/images/6FA355D7BE6EB3A28863AACC75F0F151E76AEAEB162E04FDB36614D6C6521777.jpg","binghd":"https://www.bing.com/th?id=OHR.LiquidNitrogen_JA-JP8558852359_1920x1080.jpg&rf=LaDigue_1920x1080.jpg&pid=hp","bingtmb":"https://www.bing.com/th?id=OHR.LiquidNitrogen_JA-JP8558852359_tmb.jpg"}}