{"title":"Rose orientale","caption":"Rose orientale","desc":"Chaque année, des millions de roses sont récoltées au mois de mai et juin dans les gorges du Dadès, connues également sous le nom de Vallée des roses ou encore Vallée des mille kasbahs, en raison des multiples forteresses que l’on y trouve. Le fleuve Asif M’Goun s’écoule entre les canyons, depuis l’Atlas, irriguant les vallées en contrebas.","copyright":"Ruines d’une kasbah à Kelaat M'Gouna, Maroc (© Leonid Andronov/Getty Images)","copyrightlink":"/search?q=Gorges+du+Dad%c3%a8s&form=hpcapt&filters=HpDate%3a%2220200501_2200%22","date":"20200501","image":{"name":"OHR.KasbahRoses_FR-FR8629408296.jpg","hd":"/images/0C563DB71B7C98C673F32B7FD66869914FE6D76B6450BB28B9D63CABCACE33A1.jpg","tmb":"/images/3A49759D4EAA5AD066D28F48A0AB2FCC8FF245F813B313747CB6372B98F2EB32.jpg","binghd":"https://www.bing.com/th?id=OHR.KasbahRoses_FR-FR8629408296_1920x1080.jpg&rf=LaDigue_1920x1080.jpg&pid=hp","bingtmb":"https://www.bing.com/th?id=OHR.KasbahRoses_FR-FR8629408296_tmb.jpg"}}