{"desc":"在世界水彩画月，你可以尽情的发挥你的创造力。当然，你可能无法像温斯洛·霍默一样画出'Rocky Shore'这样的标志性作品，但你所需要的只是一套水彩颜料，来激发你自己独特的画作。毕竟艺术是一种宣泄的方式。正如鲍勃·罗斯曾经说过：“在绘画中，你拥有无限的力量。你有能力移山，你可以弯曲河流。”","copyright":"油画中的现实感 波士顿美术馆收藏的画家温斯洛·霍默的水彩画'Rocky Shore' (© Alamy)","copyrightonly":"© Alamy","date":"20180724","divider":1,"image":{"name":"OHR.HomerWatercolor_ZH-CN11392693224","hd":"/images/E904521EF08638275747BB714C4EA37671BFE3FFCC5CDB144E5AE82DDED0C74C.jpg","binghd":"https://www.bing.com/th?id=OHR.HomerWatercolor_ZH-CN11392693224_1920x1080.jpg&rf=LaDigue_1920x1080.jpg&pid=hp","bingtmb":"https://www.bing.com/th?id=OHR.HomerWatercolor_ZH-CN11392693224_tmb.jpg"}}