{"desc":"位于亚利桑那州中部的花岗岩峡谷里充满了陡峭的悬崖峭壁，这里深受很多攀岩者的青睐。沃森湖是一座在花岗岩上建造水坝时创建的水库，许多钓鱼爱好者喜欢前来这里垂钓，并吸引了许多游客乘独木舟、皮划艇和其它水上飞机。如果你想融入当地人的生活，可以从普雷斯科特出发沿着Peavine步道到达花岗岩峡谷！","copyright":"梦幻的湖水 花岗岩峡谷中的沃森湖，美国亚利桑那州 (© Tim Fitzharris/Minden Pictures)","copyrightonly":"© Tim Fitzharris/Minden Pictures","date":"20180129","divider":1,"image":{"name":"OHR.GraniteDells_ZH-CN10095346278","hd":"/images/E28474BA1A119A66465D644A282D91E42AD55364D07E49EC891E294EEA06D492.jpg","binghd":"https://www.bing.com/th?id=OHR.GraniteDells_ZH-CN10095346278_1920x1080.jpg&rf=LaDigue_1920x1080.jpg&pid=hp","bingtmb":"https://www.bing.com/th?id=OHR.GraniteDells_ZH-CN10095346278_tmb.jpg"}}