{"images":[{"startdate":"20200124","fullstartdate":"202001242300","enddate":"20200125","url":"/th?id=OHR.SouthernGate_DE-DE9569663805_1920x1080.jpg&rf=LaDigue_1920x1080.jpg&pid=hp","urlbase":"/th?id=OHR.SouthernGate_DE-DE9569663805","copyright":"Feierlichkeiten zum chinesischen Neujahrsfest in Xi'an, Volksrepublik China (© Aleksandar Plavevski/Shutterstock)","copyrightlink":"/search?q=Chinesisches+Neujahrsfest&form=hpcapt&filters=HpDate%3a%2220200124_2300%22","title":"Frohes neues Jahr! (Noch einmal!)","caption":"Frohes neues Jahr! (Noch einmal!)","copyrightonly":"© Aleksandar Plavevski/Shutterstock","desc":"Sie müssen kein Chinese sein, um das chinesische Neujahrsfest zu feiern. Unser heutiges Bild zeigt die festlich geschmückte und beleuchtete südliche Stadtmauer der Stadt Xi’an anlässlich der letztjährigen Neujahrsfeierlichkeiten im chinesischen Lunisolarkalender.","date":"25. Jan. 2020","bsTitle":"Frohes neues Jahr! (Noch einmal!)","quiz":"/search?q=Bing+homepage+quiz&filters=WQOskey:%22HPQuiz_20200124_SouthernGate%22&FORM=HPQUIZ","wp":false,"hsh":"e8f85ea286d0795217d5d236a0f2e9b1","drk":1,"top":1,"bot":1,"hs":[],"og":{"img":"https://www.bing.com/th?id=OHR.SouthernGate_DE-DE9569663805_tmb.jpg","title":"Frohes neues Jahr! (Noch einmal!)","desc":"Sie müssen kein Chinese sein, um das chinesische Neujahrsfest zu feiern. Unser heutiges Bild zeigt die festlich geschmückte und beleuchtete…","hash":"um75RSTqiJkvy1cnDnLm8acEf8dCYNaXujtGDnoPR54="}}],"tooltips":{"loading":"Wird geladen...","previous":"Vorheriges Bild","next":"Nächstes Bild","walle":"Dieses Bild steht nicht zum Download als Hintergrundbild zur Verfügung.","walls":"Dieses Bild herunterladen. Dieses Bild darf nur als Hintergrundbild verwendet werden."}}