{"desc":"薄雾似乳白色的薄纱，如梦、如幻、如诗、如画，挥不走，扯不开，斩不断，挡住了眼前湖中的小岛。岛上的山体、植物，都在雾气中若隐若现，逐渐接近才慢慢揭开这层神秘的面纱。雾气氤氲下的事物难以捉摸，总是给人一种期盼。","copyright":"雾气氤氲的小岛 芬顿湖中雨雾缭绕的小岛，苏必利尔湖省立公园，加拿大安大略省 (© Mike Grandmaison/Getty Images)","copyrightonly":"© Mike Grandmaison/Getty Images","date":"20160926","divider":1,"image":{"name":"OHR.FentonLake_ZH-CN12244750610","hd":"/images/840A8B027EB817DF729099CFBE3CE8CD168CDCD287EBCB063326546C95DAE67F.jpg","binghd":"https://www.bing.com/th?id=OHR.FentonLake_ZH-CN12244750610_1920x1080.jpg&rf=LaDigue_1920x1080.jpg&pid=hp","bingtmb":"https://www.bing.com/th?id=OHR.FentonLake_ZH-CN12244750610_tmb.jpg"}}