{"images":[{"startdate":"20200520","fullstartdate":"202005202200","enddate":"20200521","url":"/th?id=OHR.JeffHanson_ES-ES7884492227_1920x1080.jpg&rf=LaDigue_1920x1080.jpg&pid=hp","urlbase":"/th?id=OHR.JeffHanson_ES-ES7884492227","copyright":"“Paseando por Biltmore”, una pintura de Jeff Hanson (© Jeff Hanson Art)","copyrightlink":"/search?q=accesibilidad+universal&FORM=Hpcapt&filters=HpDate%3a%2220200520_2200%22","title":"La visión de un pintor ciego","caption":"La visión de un pintor ciego","copyrightonly":"© Jeff Hanson Art","desc":"La pintura que hoy te mostramos en la imagen pertenece al artista Jeff Hanson. La realizó sin apenas ver los colores que estaba aplicando porque cuando era niño se quedó prácticamente ciego después de que un tumor cerebral dañara sus nervios ópticos. Pero eso no le impide pintar ni apreciar la belleza del arte, aunque debe hacerlo de otra manera.","date":"21 de may. de 2020","quiz":"/search?q=Bing+homepage+quiz&filters=WQOskey:%22HPQuiz_20200520_JeffHanson%22&FORM=HPQUIZ","wp":false,"hsh":"cf044005a23ce1b2954002a183b98544","drk":1,"top":1,"bot":1,"hs":[],"og":{"img":"https://www.bing.com/th?id=OHR.JeffHanson_ES-ES7884492227_tmb.jpg","title":"La visión de un pintor ciego","desc":"La pintura que hoy te mostramos en la imagen pertenece al artista Jeff Hanson. La realizó sin apenas ver los colores que estaba aplicando…","hash":"TMV7c3f1U277JnNtYW+M2bxd3Zhz5hfatSNHW1eIBsY="}}],"tooltips":{"loading":"Cargando...","previous":"Imaxe anterior","next":"Seguinte imaxe","walle":"Esta imaxe non está dispoñible para descargar como fondo de escritorio.","walls":"Descargar esta imaxe. Esta imaxe só pode utilizarse como fondo de escritorio."}}