{"images":[{"startdate":"20191104","fullstartdate":"201911042300","enddate":"20191105","url":"/th?id=OHR.CamelsBalloons_ES-ES9965512263_1920x1080.jpg&rf=LaDigue_1920x1080.jpg&pid=hp","urlbase":"/th?id=OHR.CamelsBalloons_ES-ES9965512263","copyright":"Feria de camellos de Púshkar, Rajastán, India (© Anand Purohit/Getty Images)","copyrightlink":"/search?q=feria+de+pushkar&FORM=hpcapt&filters=HpDate%3a%2220191104_2300%22","title":"Navegantes en el mar de dunas","caption":"Navegantes en el mar de dunas","copyrightonly":"© Anand Purohit/Getty Images","desc":"Bienvenidos al mayor mercado de camellos de la India. Lo que veis en nuestra foto de hoy es la feria de Púshkar, en el estado de Rajastán. Cada año, miles de criadores cruzan las montañas y el desierto de Thar para hacer negocios en este lugar. Y miles de turistas se acercan para disfrutar de un espectáculo único en el mundo que te dejará con la boca abierta.","date":"5 de nov. de 2019","bsTitle":"Navegantes en el mar de dunas","quiz":"/search?q=Bing+homepage+quiz&filters=WQOskey:%22HPQuiz_20191104_CamelsBalloons%22&FORM=HPQUIZ","wp":true,"hsh":"2caaf9a2cd940c0d7b5ac7cf042c4a66","drk":1,"top":1,"bot":1,"hs":[],"og":{"img":"https://www.bing.com/th?id=OHR.CamelsBalloons_ES-ES9965512263_tmb.jpg","title":"Navegantes en el mar de dunas","desc":"Bienvenidos al mayor mercado de camellos de la India. Lo que veis en nuestra foto de hoy es la feria de Púshkar, en el estado de Rajastán…","hash":"n6xblqIuEtw3lYkOivB7ew60kA1KxJbkjV0kO+N89/M="}}],"tooltips":{"loading":"Cargando...","previous":"Imagen anterior","next":"Siguiente imagen","walle":"Esta imagen no está disponible para su descarga como fondo de pantalla.","walls":"Descarga la imagen. Solo se puede usar como papel tapiz."}}