{"images":[{"startdate":"20191205","fullstartdate":"201912052300","enddate":"20191206","url":"/th?id=OHR.NambungPinnacles_FR-FR7422003067_1920x1080.jpg&rf=LaDigue_1920x1080.jpg&pid=hp","urlbase":"/th?id=OHR.NambungPinnacles_FR-FR7422003067","copyright":"Le désert des Pinacles dans le parc national de Nambung, Australie Occidentale (© Frank Krahmer/Getty Images Plus)","copyrightlink":"/search?q=pinnacles+d%c3%a9sert&form=hpcapt&filters=HpDate%3a%2220191205_2300%22","title":"Pendant ce temps, en Australie…","caption":"L'originalité des sites touristiques australiens","copyrightonly":"© Frank Krahmer/Getty Images Plus","desc":"Non, ce que vous voyez n’est pas le décor du dernier Mad Max ! L’image d’aujourd’hui présente l’une des destinations les plus pittoresques de l’Australie Occidentale, le désert des Pinacles situé dans le parc national de Nambung. Abritant des milliers de ces piliers de calcaire qui, pour certains, sont là depuis des millions d’années, la question à savoir comment ces pinacles furent formés fait débat. Cependant, la plupart pensent qu’ils sont le résultat de coquillages qui se sont petit à petit enterrés dans le sable et qui furent érodés par la suite par Mère Nature elle-même.","date":"6 déc. 2019","bsTitle":"Pendant ce temps, en Australie…","quiz":"/search?q=Bing+homepage+quiz&filters=WQOskey:%22HPQuiz_20191205_NambungPinnacles%22&FORM=HPQUIZ","wp":true,"hsh":"53264e5f2f554d49ea9451a0f500ff20","drk":1,"top":1,"bot":1,"hs":[],"og":{"img":"https://www.bing.com/th?id=OHR.NambungPinnacles_FR-FR7422003067_tmb.jpg","title":"L'originalité des sites touristiques australiens","desc":"Non, ce que vous voyez n’est pas le décor du dernier Mad Max ! L’image d’aujourd’hui présente l’une des destinations les plus pittoresques…","hash":"MFfWXZZR6IRURXcXTOmechnG6P+1sa4bTB7wp4bTdIs="}}],"tooltips":{"loading":"Chargement en cours...","previous":"Image précédente","next":"Image suivante","walle":"Cette image n’est pas disponible pour téléchargement en tant que papier peint.","walls":"Téléchargez cette image. L’utilisation de cette image est réservée à des fins de papier peint uniquement."}}