{"title":"Frohes neues Jahr! (Noch einmal!)","caption":"Frohes neues Jahr! (Noch einmal!)","desc":"Sie müssen kein Chinese sein, um das chinesische Neujahrsfest zu feiern. Unser heutiges Bild zeigt die festlich geschmückte und beleuchtete südliche Stadtmauer der Stadt Xi’an anlässlich der letztjährigen Neujahrsfeierlichkeiten im chinesischen Lunisolarkalender.","copyright":"Feierlichkeiten zum chinesischen Neujahrsfest in Xi'an, Volksrepublik China (© Aleksandar Plavevski/Shutterstock)","copyrightlink":"/search?q=Chinesisches+Neujahrsfest&form=hpcapt&filters=HpDate%3a%2220200124_2300%22","date":"20200124","image":{"name":"OHR.SouthernGate_DE-DE9569663805.jpg","hd":"/images/552C35E8695E7C68408462ABD651E85FFEBADD7111136E1EAF9CC27163B54067.jpg","tmb":"/images/7C894FE351B1F4D9C7F3DF72AA99001DF81F78D5F0F617BAA547ACD021705D2D.jpg","binghd":"https://www.bing.com/th?id=OHR.SouthernGate_DE-DE9569663805_1920x1080.jpg&rf=LaDigue_1920x1080.jpg&pid=hp","bingtmb":"https://www.bing.com/th?id=OHR.SouthernGate_DE-DE9569663805_tmb.jpg"}}