{"images":[{"startdate":"20191002","fullstartdate":"201910021500","enddate":"20191003","url":"/th?id=OHR.AdelieBreeding_JA-JP2463616125_1920x1080.jpg&rf=LaDigue_1920x1080.jpg&pid=hp","urlbase":"/th?id=OHR.AdelieBreeding_JA-JP2463616125","copyright":"｢アデリーペンギン｣南極, ポゼッション島 (© Tui De Roy/Minden Pictures)","copyrightlink":"/search?q=%e3%82%a2%e3%83%87%e3%83%aa%e3%83%bc%e3%83%9a%e3%83%b3%e3%82%ae%e3%83%b3&form=hpcapt&filters=HpDate%3a%2220191002_1500%22","title":"アデリーペンギン、繁殖の季節","caption":"｢アデリーペンギン｣南極, ポゼッション島","copyrightonly":"© Tui De Roy/Minden Pictures","desc":"10月から12月にかけて、南極は短い夏を迎えます。この短い夏はアデリーペンギンの繁殖の季節。南極周辺の海域に暮らしていたアデリーペンギンたちは、今の時期になると岩場の海岸に集まり巣作りを始めます…","date":"2019 年 10 月 3 日","bsTitle":"アデリーペンギン、繁殖の季節","quiz":"/search?q=Bing+homepage+quiz&filters=WQOskey:%22HPQuiz_20191002_AdelieBreeding%22&FORM=HPQUIZ","wp":true,"hsh":"b40238561f7721393acc0c4de9517e52","drk":1,"top":1,"bot":1,"hs":[],"og":{"img":"https://www.bing.com/th?id=OHR.AdelieBreeding_JA-JP2463616125_tmb.jpg","title":"｢アデリーペンギン｣南極, ポゼッション島","desc":"10月から12月にかけて、南極は短い夏を迎えます。この短い夏はアデリーペンギンの繁殖の季節。南極周辺の海域に暮らしていたアデリーペンギンたちは、今の時期になると…","hash":"6EOI0phDXQ/0qq/iajt8JU0ue993NX31CsuLXtF384g="}}],"tooltips":{"loading":"読み込み中...","previous":"前の画像へ","next":"次の画像へ","walle":"この画像を壁紙としてダウンロードすることはできません。","walls":"この画像をダウンロードできます。画像の用途は壁紙に限定されています。"}}