{"desc":"51年前，美国、英国和苏联生效了《外层空间条约》。此后，至少有107个其它国家成为该条约的缔约国，另外还有更多的国家正在致力于承认该条约。该条约本质上是一项协议，即空间探索只能是为了造福全人类。任何大规模杀伤性武器都不能用在探索太空的道路上。壁纸中这张土星的照片是由美国宇航局发射的哈勃太空望远镜拍摄的，如此震撼而美丽的土星被黑暗神秘的外太空衬托的更加辉煌。","copyright":"自带光环才最酷 哈勃望远镜下的土星 (© NASA)","copyrightonly":"© NASA","date":"20181009","divider":1,"image":{"name":"OHR.HubbleSaturn_ZH-CN12020278371","hd":"/images/9A92FB7D44940C63975E70541A183A96B5FD84ED1CD0EE32EC3616C3043FDFE6.jpg","binghd":"https://www.bing.com/th?id=OHR.HubbleSaturn_ZH-CN12020278371_1920x1080.jpg&rf=LaDigue_1920x1080.jpg&pid=hp","bingtmb":"https://www.bing.com/th?id=OHR.HubbleSaturn_ZH-CN12020278371_tmb.jpg"}}