{"images":[{"startdate":"20191226","fullstartdate":"201912262300","enddate":"20191227","url":"/th?id=OHR.KinderdijkSkating_ES-ES1599945190_1920x1080.jpg&rf=LaDigue_1920x1080.jpg&pid=hp","urlbase":"/th?id=OHR.KinderdijkSkating_ES-ES1599945190","copyright":"Patinando por los canales de Kinderdijk, Países Bajos (© Lourens Smak/Alamy)","copyrightlink":"/search?q=kinderdijk+molinos&FORM=hpcapt&filters=HpDate%3a%2220191226_2300%22","title":"Diversión sobre el hielo","caption":"Un país bajo el nivel del mar","copyrightonly":"© Lourens Smak/Alamy","desc":"Viajamos hoy hasta Kinderdijk, en los Países Bajos, para patinar entre molinos de viento. Cada invierno, cuando bajan las temperaturas, los canales se congelan y los holandeses salen a divertirse sobre el hielo. Tienen kilómetros y kilómetros de pista que incluso les permiten ir de un pueblo a otro deslizándose.","date":"27 de dic. de 2019","bsTitle":"Diversión sobre el hielo","quiz":"/search?q=Bing+homepage+quiz&filters=WQOskey:%22HPQuiz_20191226_KinderdijkSkating%22&FORM=HPQUIZ","wp":false,"hsh":"732dd5bbc00bcd53e78edd7058b7c506","drk":1,"top":1,"bot":1,"hs":[],"og":{"img":"https://www.bing.com/th?id=OHR.KinderdijkSkating_ES-ES1599945190_tmb.jpg","title":"Un país bajo el nivel del mar","desc":"Viajamos hoy hasta Kinderdijk, en los Países Bajos, para patinar entre molinos de viento. Cada invierno, cuando bajan las temperaturas, los…","hash":"eWq69IJjTNIRuHLVier/brzYTeU/VCCiVs3djcmKIvY="}}],"tooltips":{"loading":"Cargando...","previous":"Imagen anterior","next":"Siguiente imagen","walle":"Esta imagen no está disponible para su descarga como fondo de pantalla.","walls":"Descarga la imagen. Solo se puede usar como papel tapiz."}}