{"images":[{"startdate":"20191119","fullstartdate":"201911190500","enddate":"20191120","url":"/th?id=OHR.ZionBirthday_FR-CA3182660245_1920x1080.jpg&rf=LaDigue_1920x1080.jpg&pid=hp","urlbase":"/th?id=OHR.ZionBirthday_FR-CA3182660245","copyright":"Couleurs d'automne dans le Parc national de Zion, Utah (© pabradyphoto/Getty Images)","copyrightlink":"/search?q=Parc+national+de+Zion&form=hpcapt","title":"","quiz":"/search?q=Bing+homepage+quiz&filters=WQOskey:%22HPQuiz_20191119_ZionBirthday%22&FORM=HPQUIZ","wp":true,"hsh":"82aafecd2d5e17c7ea22843eaa9d9860","drk":1,"top":1,"bot":1,"hs":[],"og":{"img":"https://www.bing.com/th?id=OHR.ZionBirthday_FR-CA3182660245_tmb.jpg","title":"Page d’accueil d’aujourd’hui","desc":"Regardez ce qui est à la une de la page d'accueil Bing aujourd'hui !","hash":"nNmN9U9+24cXsrYQYlNGZ9cu4dO3RbgaiPBYOgdi6pE="}}],"tooltips":{"loading":"Chargement en cours...","previous":"Image précédente","next":"Image suivante","walle":"Cette image n’est pas disponible pour téléchargement en tant que papier peint.","walls":"Téléchargez cette image. L’utilisation de cette image est réservée à des fins de papier peint uniquement."}}