{"images":[{"startdate":"20200506","fullstartdate":"202005062300","enddate":"20200507","url":"/th?id=OHR.EagleSwoop_EN-GB3415023700_1920x1080.jpg&rf=LaDigue_1920x1080.jpg&pid=hp","urlbase":"/th?id=OHR.EagleSwoop_EN-GB3415023700","copyright":"Golden eagle flying over a field, Glenfeshie (© Blickwinkel/Alamy Stock Photo)","copyrightlink":"/search?q=Golden+eagle&form=hpcapt&filters=HpDate%3a%2220200506_2300%22","title":"Winging it","caption":"Winging it over the Highlands","copyrightonly":"© Blickwinkel/Alamy Stock Photo","desc":"Is it a bird? Is it a plane? You’d be forgiven for briefly mistaking this magnificent beast for a small aircraft as it flies overhead. The UK’s second-largest bird of prey (after the white-tailed eagle), the golden eagle boasts a huge wingspan of over two metres (7ft) which it puts to good use, flying low over land before striking its prey with those impressive yellow talons. As it swoops over wild open moorland and mountains, its razor-sharp eyesight allows it to spot red grouse, ptarmigans, mountain hares and other prey from miles away.","date":"7 May 2020","bsTitle":"Winging it","quiz":"/search?q=Bing+homepage+quiz&filters=WQOskey:%22HPQuiz_20200506_EagleSwoop%22&FORM=HPQUIZ","wp":true,"hsh":"d64f47fda3ef0e2d9c7c424a304d8944","drk":1,"top":1,"bot":1,"hs":[],"og":{"img":"https://www.bing.com/th?id=OHR.EagleSwoop_EN-GB3415023700_tmb.jpg","title":"Winging it over the Highlands","desc":"Is it a bird? Is it a plane? You’d be forgiven for briefly mistaking this magnificent beast for a small aircraft as it flies overhead. The…","hash":"XBvRrU2Tzt/VHVpymfMkhftNGkObopBOS7A0pYEP4P4="}}],"tooltips":{"loading":"Loading...","previous":"Previous image","next":"Next image","walle":"This image is not available to download as wallpaper.","walls":"Download this image. Use of this image is restricted to wallpaper only."}}