{"desc":"圆形谷仓的设计利用了地球引力和谷仓内的中央仓筒实现了把干草从阁楼运到畜棚层的可能。虽然这个设计是为了减少工作量，但是它依旧没有传统四方谷仓受欢迎。美国大部分圆形谷仓建于19世纪中期到20世纪30年代，比如现在看到的Fromme-Birney谷仓，就是建于1912年。如今， Fromme-Birney 圆形谷仓博物馆已记入《国家史迹名录》。","copyright":"圆形谷仓 马林维尔的Fromme-Birney Round Barn博物馆的内顶，堪萨斯州，美国 (© Garret Suhrie/Tandem Stills + Motion)","copyrightonly":"© Garret Suhrie/Tandem Stills + Motion","date":"20161212","divider":1,"image":{"name":"OHR.CircularBarn_ZH-CN10350401093","hd":"/images/9570932EF2C7FF339EDAF476CF19BD31A5905CC08BD4C85E714D52409F376648.jpg","binghd":"https://www.bing.com/th?id=OHR.CircularBarn_ZH-CN10350401093_1920x1080.jpg&rf=LaDigue_1920x1080.jpg&pid=hp","bingtmb":"https://www.bing.com/th?id=OHR.CircularBarn_ZH-CN10350401093_tmb.jpg"}}