{"title":"Wandern durch den Schnee","caption":"Wandern durch den Schnee","desc":"Ob die Rentiere auf unserer Startseite noch vor wenigen Tagen dem Weihnachtsmann zu Diensten waren und seinen Schlitten gezogen haben, können wir Ihnen nicht beantworten. Aber Rentiere werden bekanntermaßen mit dem Wunder der Feiertage in Verbindung gebracht. Die Tiere, die in Nordamerika als Karibus bekannt sind, sind dafür geeignet, um in kalten, rauen arktischen Regionen zu leben. Sie sind so gebaut, dass sie den kalten Temperaturen mit Hilfe ihres dicken, dichten Felles trotzen können, und dass ihre Nasen die Luft erwärmen, bevor sie sie einatmen.","copyright":"Rentierherde in Norwegen (© Lena Granefelt/plainpicture)","copyrightlink":"/search?q=Rentier&form=hpcapt&filters=HpDate%3a%2220191227_2300%22","date":"20191227","image":{"name":"OHR.ReindeerNorway_DE-DE1038297951.jpg","hd":"/images/5E7E5596A7059D7ECA9D852382C8BE4E8AA3375631B3E5638B880D6D98D89200.jpg","tmb":"/images/0F2514742D7E58229258EE55CDCE7583C88D9D2228856388938B808E5E4F355A.jpg","binghd":"https://www.bing.com/th?id=OHR.ReindeerNorway_DE-DE1038297951_1920x1080.jpg&rf=LaDigue_1920x1080.jpg&pid=hp","bingtmb":"https://www.bing.com/th?id=OHR.ReindeerNorway_DE-DE1038297951_tmb.jpg"}}