{"title":"Celebrating Australia Day across the country","caption":"Celebrating Australia Day across the country","desc":"No matter where you find yourself today, there’s always plenty to do on Australia Day, and this year is no exception. If you’re in Sydney, annual firework displays across the harbour, like the ones you see today, will light up the night sky. For those in Victoria, on the other hand, why not check out the Official Flag Raising ceremony, closely followed by the Australia Day Parade – featuring more than 1000 participants from over 80 community and cultural groups.","copyright":"Sydney Opera House Australia Day celebration in 2018 (© Michal Ziarno/Shutterstock)","copyrightlink":"/search?q=Australia+Day&form=hpcapt&filters=HpDate%3a%2220200125_1300%22","date":"20200125","image":{"name":"OHR.AustraliaDayOpera_EN-AU9693064147.jpg","hd":"/images/325DCB0561BF0A33338F004661BF30452A5319858C8A357F3AE938D241824877.jpg","tmb":"/images/D22435DF65286100E4858F654D40FAF527A883B71D33B9CA4282A0A3FD525DC2.jpg","binghd":"https://www.bing.com/th?id=OHR.AustraliaDayOpera_EN-AU9693064147_1920x1080.jpg&rf=LaDigue_1920x1080.jpg&pid=hp","bingtmb":"https://www.bing.com/th?id=OHR.AustraliaDayOpera_EN-AU9693064147_tmb.jpg"}}