{"images":[{"startdate":"20191208","fullstartdate":"201912082300","enddate":"20191209","url":"/th?id=OHR.BlueChip_ES-ES3235950657_1920x1080.jpg&rf=LaDigue_1920x1080.jpg&pid=hp","urlbase":"/th?id=OHR.BlueChip_ES-ES3235950657","copyright":"Detalle de un microchip (© Bobkov Evgeniy/Shutterstock)","copyrightlink":"/search?q=ciencias+de+la+computaci%c3%b3n&FORM=hpcapt&filters=HpDate%3a%2220191208_2300%22","title":"Descifra el código","caption":"Descifra el código","copyrightonly":"© Bobkov Evgeniy/Shutterstock","desc":"Si alguna vez has tenido la curiosidad de saber cómo funcionan los ordenadores, estás de enhorabuena, porque hoy comienza la Semana de la Educación en Ciencias de la Computación. Se trata de un evento anual que ofrece “Horas de Código” para inspirar a los estudiantes de primaria y secundaria, pero también a todos aquellos que quieran profundizar en esta disciplina.","date":"2019, dic. 9","quiz":"/search?q=Bing+homepage+quiz&filters=WQOskey:%22HPQuiz_20191208_BlueChip%22&FORM=HPQUIZ","wp":true,"hsh":"41987359311438ea601aa4d0d3c3ac82","drk":1,"top":1,"bot":1,"hs":[],"og":{"img":"https://www.bing.com/th?id=OHR.BlueChip_ES-ES3235950657_tmb.jpg","title":"Descifra el código","desc":"Si alguna vez has tenido la curiosidad de saber cómo funcionan los ordenadores, estás de enhorabuena, porque hoy comienza la Semana de la…","hash":"HmsjWQW8vnhofrljfKbo3RcRSz2mooCIp2ZN/17L29Q="}}],"tooltips":{"loading":"Kargatzen...","previous":"Aurreko irudia","next":"Hurrengo irudia","walle":"Irudi hau ezin da horma-paper gisa deskargatu.","walls":"Deskargatu irudia. Irudi hau horma-irudi gisa erabil daiteke soilik."}}