{"desc":"Blanchard Springs Caverns洞穴是世界上最壮观和精心开发的洞穴之一。进入洞穴之前，游客会观看一部短片，介绍他们即将探索的地下世界。全年的各种旅游活动为游客提供了洞穴的不同视角以及不同的难度。美丽的灯光加上不断变化的流石，让游客流连忘返。","copyright":"身处黑暗却温暖如你 阿肯色州的温泉洞穴 (© Garret Suhrie/Tandem Stills + Motion)","copyrightonly":"© Garret Suhrie/Tandem Stills + Motion","date":"20170310","divider":1,"image":{"name":"OHR.BlanchardSprings_ZH-CN10814394195","hd":"/images/4E5A4745ED33CDF778E4DC567B0BBEF10E1D9B92C3A4456FC093DCF44FC6B1BB.jpg","binghd":"https://www.bing.com/th?id=OHR.BlanchardSprings_ZH-CN10814394195_1920x1080.jpg&rf=LaDigue_1920x1080.jpg&pid=hp","bingtmb":"https://www.bing.com/th?id=OHR.BlanchardSprings_ZH-CN10814394195_tmb.jpg"}}