{"images":[{"startdate":"20191222","fullstartdate":"201912221830","enddate":"20191223","url":"/th?id=OHR.OrchhaPalace_EN-IN9280856111_1920x1080.jpg&rf=LaDigue_1920x1080.jpg&pid=hp","urlbase":"/th?id=OHR.OrchhaPalace_EN-IN9280856111","copyright":"Orchha Palace on a misty morning at sunrise (© Luigi Vaccarella/Sime/eStock Photo)","copyrightlink":"/search?q=orchha+palace&FORM=HPCAPT&filters=HpDate%3a%2220191222_1830%22","title":"The Orchha palace on a misty morning","caption":"The Orchha palace on a misty morning","copyrightonly":"© Luigi Vaccarella/Sime/eStock Photo","desc":"Sunrise can be quite a pleasant sight on a misty morning at Orchha Palace, Madhya Pradesh. Of course, we advise you to dress warm if you visit in the winter. Most probably, you’d experience below 10-degree temperatures in the morning around this time of the year. Alternatively, you could just sit back and enjoy the view on today’s homepage!","date":"Dec 23, 2019","quiz":"/search?q=Bing+homepage+quiz&filters=WQOskey:%22HPQuiz_20191222_OrchhaPalace%22&FORM=HPQUIZ","wp":true,"hsh":"d9e4335093150733f60cd7154a744868","drk":1,"top":1,"bot":1,"hs":[],"og":{"img":"https://www.bing.com/th?id=OHR.OrchhaPalace_EN-IN9280856111_tmb.jpg","title":"The Orchha palace on a misty morning","desc":"Sunrise can be quite a pleasant sight on a misty morning at Orchha Palace, Madhya Pradesh. Of course, we advise you to dress warm if you…","hash":"aeMdbgTLbN6nAu8klljUcR8gr944jr0gpeskb2S7M0M="}}],"tooltips":{"loading":"లోడ్ చేస్తోంది...","previous":"మునుపటి చిత్రం","next":"తదుపరి చిత్రం","walle":"ఈ చిత్రం వాల్‌పేపర్‌గా డౌన్‌లోడ్ చేయడానికి అందుబాటులో లేదు.","walls":"ఈ చిత్రాన్ని డౌన్‌లోడ్ చేయండి. ఈ చిత్రం వినియోగం వాల్‌పేపర్‌కి మాత్రమే పరిమితం చేయబడింది."}}