{"title":"« Bouh !»","caption":"Danse gastronomique","desc":"On nous recommande souvent de danser comme si personne ne nous regardait mais ici, en Floride, il y a fort à parier que cette aigrette roussâtre se produise en fait devant une foule d’ornithologues enthousiastes.  Les membres de cette espèce sont connus pour avoir une manière de se nourrir ressemblant à une danse frénétique. Alors qu’elle chasse sa proie, l’aigrette roussâtre sautille, titube et bondit, tout en positionnant ses ailes de façon à se protéger des rayons du soleil et pouvoir ainsi empaler un poisson sans problème, ni scrupules.","copyright":"Une aigrette roussâtre chasse dans le parc du Fort de Soto, Floride, États-Unis (© Brian Lasenby/Getty Images)","copyrightlink":"/search?q=aigrette+rouss%c3%a2tre&form=hpcapt&filters=HpDate%3a%2220200130_2300%22","date":"20200130","image":{"name":"OHR.ReddishEgret_FR-FR5427125679.jpg","hd":"/images/9E4E85CDA45D5CBFAB6D04EF3A04BC7AB3656F1CF475DF08D59592D1F5439D35.jpg","tmb":"/images/966329902C688A13DFFF6C5FE4F305105BA7DD706DB9CBC1C073233CE6AAAEE1.jpg","binghd":"https://www.bing.com/th?id=OHR.ReddishEgret_FR-FR5427125679_1920x1080.jpg&rf=LaDigue_1920x1080.jpg&pid=hp","bingtmb":"https://www.bing.com/th?id=OHR.ReddishEgret_FR-FR5427125679_tmb.jpg"}}