{"images":[{"startdate":"20191027","fullstartdate":"201910270400","enddate":"20191028","url":"/th?id=OHR.NaranjoBulnes_FR-CA7644075922_1920x1080.jpg&rf=LaDigue_1920x1080.jpg&pid=hp","urlbase":"/th?id=OHR.NaranjoBulnes_FR-CA7644075922","copyright":"Sommet du Naranjo de Bulnes, dans le Parc national des pics d’Europe, dans les Asturies, en Espagne (© Anton Petrus/Getty Images)","copyrightlink":"/search?q=sommet+Naranjo+de+Bulnes&form=HPCAPT","title":"","quiz":"/search?q=Bing+homepage+quiz&filters=WQOskey:%22HPQuiz_20191027_NaranjoBulnes%22&FORM=HPQUIZ","wp":true,"hsh":"7e9006eb786d86d6f157bb70c7e60a29","drk":1,"top":1,"bot":1,"hs":[],"og":{"img":"https://www.bing.com/th?id=OHR.NaranjoBulnes_FR-CA7644075922_tmb.jpg","title":"Page d’accueil d’aujourd’hui","desc":"Regardez ce qui est à la une de la page d'accueil Bing aujourd'hui !","hash":"nNmN9U9+24cXsrYQYlNGZ9cu4dO3RbgaiPBYOgdi6pE="}}],"tooltips":{"loading":"Chargement en cours...","previous":"Image précédente","next":"Image suivante","walle":"Cette image n’est pas disponible pour téléchargement en tant que papier peint.","walls":"Téléchargez cette image. L’utilisation de cette image est réservée à des fins de papier peint uniquement."}}